rootfoldersearch/__init__.py
rootfoldersearch-0.0.2.dist-info/LICENSE
rootfoldersearch-0.0.2.dist-info/METADATA
rootfoldersearch-0.0.2.dist-info/WHEEL
rootfoldersearch-0.0.2.dist-info/top_level.txt
rootfoldersearch-0.0.2.dist-info/RECORD
