Metadata-Version: 2.1
Name: rootfoldersearch
Version: 0.0.2
Summary: This package finds the root directory of a project by traversing the ancestors directories starting at a given path.
Home-page: https://github.com/jlcastillo/rootfoldersearch
Author: jlcastillo
Author-email: 
License: UNKNOWN
Platform: UNKNOWN
Classifier: Programming Language :: Python :: 3
Classifier: License :: OSI Approved :: MIT License
Classifier: Operating System :: OS Independent
Requires-Python: >=3.0
